{
  "_id": "6760ad706c5e0d271ce34f5a",
  "_name": "item_ammo_box_556x45",
  "_parent": "543be5cb4bdc2deb348b4568",
  "_props": {
    "AnimationVariantsNumber": 0,
    "BackgroundColor": "yellow",
    "CanRequireOnRagfair": false,
    "CanSellOnRagfair": false,
    "ConflictingItems": [],
    "Description": "ammo_box_556x45_xx_m193ball",
    "DiscardLimit": -1,
    "DiscardingBlock": false,
    "DropSoundType": "None",
    "ExamineExperience": 50,
    "ExamineTime": 1,
    "ExaminedByDefault": true,
    "ExtraSizeDown": 0,
    "ExtraSizeForceAdd": false,
    "ExtraSizeLeft": 0,
    "ExtraSizeRight": 0,
    "ExtraSizeUp": 0,
    "Height": 2,
    "HideEntrails": true,
    "InsuranceDisabled": false,
    "IsAlwaysAvailableForInsurance": false,
    "IsLockedafterEquip": false,
    "IsSpecialSlotOnly": false,
    "IsUnbuyable": false,
    "IsUndiscardable": false,
    "IsUngivable": false,
    "IsUnremovable": false,
    "IsUnsaleable": false,
    "ItemSound": "ammo_pack_generic",
    "LootExperience": 0,
    "MergesWithChildren": false,
    "Name": "ammo_box_556x45_xx_m193ball",
    "NotShownInSlot": false,
    "Prefab": {
      "path": "nato_556_box.bundle",
      "rcid": ""
    },
    "QuestItem": false,
    "QuestStashMaxCount": 0,
    "RagFairCommissionModifier": 1,
    "RarityPvE": "Rare",
    "RepairCost": 0,
    "RepairSpeed": 0,
    "ShortName": "ammo_box_556x45_xx_m193ball",
    "StackMaxRandom": 420,
    "StackMaxSize": 1,
    "StackMinRandom": 420,
    "StackObjectsCount": 1,
    "StackSlots": [
      {
        "_id": "6760ad8d8fb540a9fa41391a",
        "_max_count": 420,
        "_name": "cartridges",
        "_parent": "6760ad706c5e0d271ce34f5a",
        "_props": {
          "filters": [
            {
              "Filter": [
                "54527a984bdc2d4e668b4567"
              ]
            }
          ]
        },
        "_proto": "5748538b2459770af276a261"
      }
    ],
    "Unlootable": false,
    "UnlootableFromSide": [],
    "UnlootableFromSlot": "FirstPrimaryWeapon",
    "UsePrefab": {
      "path": "",
      "rcid": ""
    },
    "Weight": 7.1,
    "Width": 2,
    "ammoCaliber": "Caliber556x45NATO"
  },
  "_type": "Item"
}